{
  "type": "object",
  "properties": {
    "id": {
      "$ref": "definitions.json#/definitions/id"
    },
    "descriptors": {
      "type": "object",
      "properties": {
        "name": {
          "const": "concat"
        },
        "outputType": {
          "$ref": "definitions.json#/definitions/streamTypes/event"
        },
        "inputType": {
          "$ref": "definitions.json#/definitions/streamTypes/event"
        }
      }
    },
    "parameters": {},
    "outputs": {
      "$ref": "definitions.json#/definitions/output"
    },
    "input": {
      "$ref": "definitions.json#/definitions/input"
    },
    "function": {
      "const": "concat()"
    },
    "hint": {
      "const": "Concatenates the output of multiple Observables so that they act like a single Observable, with all of the items emitted by the first Observable being emitted before any of the items emitted by the second Observable (and so forth, if there are more than two)."
    }
  },
  "required": [
    "id",
    "parameters",
    "outputs",
    "input"
  ],
  "additionalProperties": false
}